xpdc/__init__.py
xpdc/screenshot.py
xpdc/utils.py
xpdc/_base/__init__.py
xpdc/_base/connection.py
xpdc/_base/device.py
xpdc/adb/__init__.py
xpdc/adb/connection.py
xpdc/adb/device.py
xpdc/hdc/__init__.py
xpdc/hdc/connection.py
xpdc/hdc/device.py
xpdc/resource/__init__.py
xpdc-0.1.1.dist-info/licenses/LICENSE
xpdc-0.1.1.dist-info/METADATA
xpdc-0.1.1.dist-info/WHEEL
xpdc-0.1.1.dist-info/top_level.txt
xpdc-0.1.1.dist-info/RECORD
