Metadata-Version: 2.4
Name: xpdc
Version: 0.1.1
Summary: XPDC (X-Platform Device Connector) is designed to bridge the gap between devices across multiple platforms (Android, HarmonyOS, iOS).
Author-email: lanbaoshen <lanbaoshen@icloud.com>
Requires-Python: >=3.11
License-File: LICENSE
Requires-Dist: loguru>=0.7.3
Requires-Dist: pillow>=12.1.0
Dynamic: license-file
